tap_datadog_rum/__init__.py
tap_datadog_rum/api_client.py
tap_datadog_rum/schema_mapper.py
tap_datadog_rum-0.8.2.dist-info/LICENSE
tap_datadog_rum-0.8.2.dist-info/METADATA
tap_datadog_rum-0.8.2.dist-info/WHEEL
tap_datadog_rum-0.8.2.dist-info/entry_points.txt
tap_datadog_rum-0.8.2.dist-info/top_level.txt
tap_datadog_rum-0.8.2.dist-info/RECORD
