Metadata-Version: 2.1
Name: tap-datadog-rum
Version: 0.8.2
Summary: Singer.io tap for extracting events from the Datadog Real User Monitoring (RUM) API
Home-page: http://github.com/shkolnik/tap-datadog-rum
Author: James Shkolnik (js@gusto.com)
Classifier: Programming Language :: Python :: 3 :: Only
License-File: LICENSE
Requires-Dist: singer-python
Requires-Dist: datadog-api-client (>=2.2)
Requires-Dist: datadog-api-client (<3)
